vvault/__init__.py
vvault/logger.py
vvault/vault.py
vvault-0.0.4.dist-info/LICENSE
vvault-0.0.4.dist-info/METADATA
vvault-0.0.4.dist-info/WHEEL
vvault-0.0.4.dist-info/RECORD
