Metadata-Version: 2.1
Name: vvault
Version: 0.0.4
Summary: Python Client for vault
Author: StepanGavrilov
Author-email: gavrilovstepan78@gmail.com
Requires-Python: >=3.11,<4.0
Classifier: Operating System :: OS Independent
Classifier: Programming Language :: Python :: 3
Classifier: Programming Language :: Python :: 3.11
Requires-Dist: hvac (>=1.1.0,<2.0.0)
Requires-Dist: pydantic (>=1.10.6,<2.0.0)
Requires-Dist: pyyaml (>=6.0,<7.0)
